clehrity/__init__.py
clehrity/__main__.py
clehrity/changepoints.py
clehrity/py.typed
clehrity-0.0.1.dist-info/LICENSE
clehrity-0.0.1.dist-info/METADATA
clehrity-0.0.1.dist-info/WHEEL
clehrity-0.0.1.dist-info/entry_points.txt
clehrity-0.0.1.dist-info/RECORD
