Metadata-Version: 2.1
Name: clehrity
Version: 0.0.1
Summary: Clehrity
Home-page: https://github.com/blengerich/clehrity
License: MIT
Author: Ben Lengerich
Author-email: blengerich@gmail.com
Requires-Python: >=3.9,<4.0
Classifier: Development Status :: 3 - Alpha
Classifier: License :: OSI Approved :: MIT License
Classifier: Programming Language :: Python :: 3
Classifier: Programming Language :: Python :: 3.9
Classifier: Programming Language :: Python :: 3.10
Classifier: Programming Language :: Python :: 3.11
Requires-Dist: anndata (>=0.10.3,<0.11.0)
Requires-Dist: click (>=8.0.1)
Requires-Dist: ebm-utils (>=0.0.3)
Requires-Dist: gam-purification (>=0.0.1,<0.0.2)
Requires-Dist: interpret (>=0.4.4,<0.5.0)
Requires-Dist: pandas-stubs (>=2.1.1.230928,<3.0.0.0)
Requires-Dist: ruptures (>=1.1.8,<2.0.0)
Requires-Dist: tornado (>=6.3.2)
Project-URL: Changelog, https://github.com/blengerich/clehrity/releases
Project-URL: Documentation, https://clehrity.readthedocs.io
Project-URL: Repository, https://github.com/blengerich/clehrity
